{"cameraMode":{"drawMode":0,"name":"Shaded","section":"Shading Mode"},"sceneLighting":true,"audioPlay":false,"sceneViewState":{"m_AlwaysRefresh":false,"showFog":true,"showSkybox":true,"showFlares":true,"showImageEffects":true,"showParticleSystems":true,"showVisualEffectGraphs":true,"m_FxEnabled":true},"in2DMode":false,"pivot":{"x":-1.7874221801757813,"y":-12.824362754821778,"z":-5.960045337677002},"rotation":{"x":0.09649508446455002,"y":0.9030957221984863,"z":-0.28115203976631167,"w":0.30995485186576846},"size":12.968345642089844,"orthographic":false}